requestlogs/__init__.py
requestlogs/base.py
requestlogs/entries.py
requestlogs/logging.py
requestlogs/middleware.py
requestlogs/storages.py
requestlogs/utils.py
requestlogs/views.py
django_requestlogs-0.8.dist-info/LICENSE.md
django_requestlogs-0.8.dist-info/METADATA
django_requestlogs-0.8.dist-info/WHEEL
django_requestlogs-0.8.dist-info/top_level.txt
django_requestlogs-0.8.dist-info/RECORD
