Metadata-Version: 2.1
Name: django-requestlogs
Version: 0.8
Summary: Audit logging for Django and Django Rest Framework
Home-page: https://github.com/Raekkeri/django-requestlogs
Download-URL: https://github.com/raekkeri/django-requestlogs/tarball/0.8
Author: Teemu Husso
Author-email: teemu.husso@gmail.com
Keywords: django,log,logging
Classifier: Development Status :: 5 - Production/Stable
Classifier: Environment :: Web Environment
Classifier: Intended Audience :: Developers
Classifier: License :: OSI Approved :: MIT License
Classifier: Operating System :: OS Independent
Classifier: Programming Language :: Python
Classifier: Programming Language :: Python :: 3 :: Only
Classifier: Programming Language :: Python :: 3.8
Classifier: Programming Language :: Python :: 3.9
Classifier: Programming Language :: Python :: 3.10
Classifier: Programming Language :: Python :: 3.11
Classifier: Programming Language :: Python :: 3.12
Classifier: Framework :: Django
Classifier: Framework :: Django :: 1.11
Classifier: Framework :: Django :: 2.2
Classifier: Framework :: Django :: 3.0
Classifier: Framework :: Django :: 3.1
Classifier: Framework :: Django :: 3.2
Classifier: Framework :: Django :: 4.0
Classifier: Framework :: Django :: 4.1
Classifier: Framework :: Django :: 4.2
Classifier: Framework :: Django :: 5.0
License-File: LICENSE.md
Requires-Dist: Django<6.0,>=1.11
Requires-Dist: djangorestframework<4.0,>=3.0
Requires-Dist: setuptools
Provides-Extra: dev
Requires-Dist: pytest; extra == "dev"
